{
  "bodyChildren" : {
    "rootArray" : [ "0d21a258-3fbc-4dc2-aecd-0909b396053c", "7b16e4f8-6352-45c9-8280-157d6ba18449", "dbd598c7-52b4-4487-893c-969c64a8924d" ],
    "widgets" : [ {
      "borderColor" : "Default",
      "borderRadius" : 4,
      "borderThickness" : 1,
      "children" : [ "4988cbaf-aed7-48d4-ab7a-f82a7d460ade", "62183ef0-2eb3-4196-80c8-e6229f7436a9", "66466454-85a6-4379-bf17-2daf9f8cd708" ],
      "heightPolicy" : "naturalSize",
      "horzGravity" : "center",
      "innerMargin" : 20,
      "name" : "HorizontalLayout22980",
      "type" : "HorizontalLayout",
      "uuid" : "046e92bb-07fc-4ce8-b400-afb9139c6b48",
      "v" : 16,
      "vertGravity" : "center",
      "w" : 700,
      "widthPolicy" : "explicit"
    }, {
      "binding" : "page.data.Technicians.fname",
      "borderColor" : "Default",
      "borderRadius" : 4,
      "borderThickness" : 0,
      "column" : -1,
      "defaultValue" : "",
      "heightPolicy" : "naturalSize",
      "horzGravity" : "left",
      "label" : "First Name",
      "labelColor" : "#000000",
      "labelStyle" : "plain",
      "name" : "inputString12",
      "optional" : false,
      "placeholder" : "",
      "row" : -1,
      "type" : "InputString",
      "uuid" : "0a9d556a-8caf-4c9b-bf67-4cbd5a28e7a8",
      "v" : 16,
      "vertGravity" : "center",
      "w" : 480,
      "widthPolicy" : "explicit"
    }, {
      "borderColor" : "Default",
      "borderRadius" : 4,
      "borderThickness" : 0,
      "fontFamily" : "Arial,Verdana",
      "fontSize" : 28,
      "fontStyle" : "normal",
      "fontWeight" : "normal",
      "heightPolicy" : "naturalSize",
      "horzGravity" : "center",
      "name" : "techpagetitle",
      "text" : "Add Technician",
      "type" : "StaticText",
      "uuid" : "0d21a258-3fbc-4dc2-aecd-0909b396053c",
      "v" : 16,
      "vertGravity" : "center",
      "widthPolicy" : "naturalSize",
      "x" : 50,
      "y" : 20
    }, {
      "binding" : "page.data.Technicians.mobile_phone",
      "borderColor" : "Default",
      "borderRadius" : 4,
      "borderThickness" : 0,
      "column" : -1,
      "defaultValue" : "",
      "heightPolicy" : "naturalSize",
      "horzGravity" : "left",
      "label" : "Mobile Phone",
      "labelColor" : "#000000",
      "labelStyle" : "plain",
      "name" : "inputString29",
      "optional" : false,
      "placeholder" : "",
      "row" : -1,
      "type" : "InputString",
      "uuid" : "17c49f1d-baa9-4331-a8a3-3675769655c6",
      "v" : 16,
      "vertGravity" : "center",
      "w" : 480,
      "widthPolicy" : "explicit"
    }, {
      "binding" : "page.data.Technicians.lname",
      "borderColor" : "Default",
      "borderRadius" : 4,
      "borderThickness" : 0,
      "column" : -1,
      "defaultValue" : "",
      "heightPolicy" : "naturalSize",
      "horzGravity" : "left",
      "label" : "Last Name",
      "labelColor" : "#000000",
      "labelStyle" : "plain",
      "name" : "inputString15",
      "optional" : false,
      "placeholder" : "",
      "row" : -1,
      "type" : "InputString",
      "uuid" : "223f3436-b51e-4670-a024-dbf95de23b9f",
      "v" : 16,
      "vertGravity" : "center",
      "w" : 480,
      "widthPolicy" : "explicit"
    }, {
      "binding" : "page.data.Technicians.username",
      "borderColor" : "Default",
      "borderRadius" : 4,
      "borderThickness" : 0,
      "column" : -1,
      "defaultValue" : "",
      "heightPolicy" : "naturalSize",
      "horzGravity" : "left",
      "label" : "Technician ID",
      "labelColor" : "#000000",
      "labelStyle" : "plain",
      "name" : "tusername",
      "optional" : false,
      "placeholder" : "",
      "row" : -1,
      "type" : "InputString",
      "uuid" : "24553139-dac0-4211-9769-5b9e6d4f9139",
      "v" : 16,
      "vertGravity" : "center",
      "w" : 480,
      "widthPolicy" : "explicit"
    }, {
      "borderColor" : "Default",
      "borderRadius" : 4,
      "borderThickness" : 0,
      "buttonBackgroundColor" : "platform",
      "buttonLabel" : "NEW Skill",
      "buttonLabelColor" : "platform",
      "buttonLabelSize" : 18,
      "buttonLabelStyle" : "plain",
      "glyphIcon" : "glyphicon-plus",
      "heightPolicy" : "naturalSize",
      "horzGravity" : "left",
      "labelAlign" : "center",
      "labelColor" : "#000000",
      "labelStyle" : "plain",
      "name" : "Button105537",
      "submitValue" : 100,
      "type" : "Button",
      "uuid" : "4988cbaf-aed7-48d4-ab7a-f82a7d460ade",
      "v" : 16,
      "vertGravity" : "center",
      "widthPolicy" : "sizeToCell"
    }, {
      "borderColor" : "Default",
      "borderRadius" : 4,
      "borderThickness" : 0,
      "buttonBackgroundColor" : "platform",
      "buttonLabel" : "Select Skills",
      "buttonLabelColor" : "platform",
      "buttonLabelSize" : 18,
      "buttonLabelStyle" : "plain",
      "glyphIcon" : "glyphicon-hand-up",
      "heightPolicy" : "naturalSize",
      "horzGravity" : "center",
      "labelAlign" : "center",
      "labelColor" : "#000000",
      "labelStyle" : "plain",
      "name" : "Button98168",
      "submitValue" : 100,
      "type" : "Button",
      "uuid" : "62183ef0-2eb3-4196-80c8-e6229f7436a9",
      "v" : 16,
      "vertGravity" : "center",
      "widthPolicy" : "sizeToCell"
    }, {
      "backgroundColor" : "default",
      "borderColor" : "Default",
      "borderRadius" : 4,
      "borderThickness" : 1,
      "cellFontColor" : "#000000",
      "cellFontFace" : "inherit",
      "cellFontSize" : 14,
      "cellFontStyle" : "plain",
      "clearOnDataArrive" : true,
      "columnDescriptors" : [ {
        "colorRules" : null,
        "dataType" : "String",
        "propertyName" : "skill",
        "selected" : false,
        "title" : "Skill"
      }, {
        "colorRules" : null,
        "dataType" : "String",
        "propertyName" : "description",
        "selected" : false,
        "title" : "Description"
      } ],
      "columnSort" : true,
      "dataStreamGroupedByFiltersString" : "",
      "dataStreamUUID" : "d4c26e3b-1ff8-4339-8606-fe22fe8cc5b8",
      "dataType" : null,
      "headerFontColor" : "#000000",
      "headerFontFace" : "inherit",
      "headerFontSize" : 14,
      "headerFontStyle" : "plain",
      "heightPolicy" : "naturalSize",
      "horzGravity" : "center",
      "name" : "DataTable928",
      "operation" : "insert",
      "rowsPerPage" : 5,
      "showPaging" : true,
      "type" : "DataTable",
      "uuid" : "63114c22-7f6a-4a4f-8967-508b3c3c922e",
      "v" : 16,
      "vertGravity" : "center",
      "w" : 700,
      "widthPolicy" : "explicit"
    }, {
      "backgroundColor" : "#ffffff",
      "borderColor" : "Default",
      "borderRadius" : 4,
      "borderThickness" : 0,
      "children" : [ "046e92bb-07fc-4ce8-b400-afb9139c6b48", "63114c22-7f6a-4a4f-8967-508b3c3c922e", "9a331708-d52b-4c10-8d96-8fca732d04ce" ],
      "heightPolicy" : "naturalSize",
      "horzGravity" : "center",
      "innerMargin" : 20,
      "name" : "VerticalContainer9124",
      "type" : "VerticalLayout",
      "uuid" : "63ebdd1d-8e60-4d7a-8a55-9a00fb94ea67",
      "v" : 16,
      "vertGravity" : "top",
      "w" : 750,
      "widthPolicy" : "explicit"
    }, {
      "borderColor" : "Default",
      "borderRadius" : 4,
      "borderThickness" : 0,
      "fontFamily" : "inherit",
      "fontSize" : 16,
      "fontStyle" : "normal",
      "fontWeight" : "normal",
      "heightPolicy" : "naturalSize",
      "horzGravity" : "right",
      "name" : "StaticText127515",
      "text" : "(click on table row to remove)",
      "type" : "StaticText",
      "uuid" : "66466454-85a6-4379-bf17-2daf9f8cd708",
      "v" : 16,
      "vertGravity" : "center",
      "widthPolicy" : "naturalSize"
    }, {
      "binding" : "page.data.Technicians.email",
      "borderColor" : "Default",
      "borderRadius" : 4,
      "borderThickness" : 0,
      "column" : -1,
      "defaultValue" : "",
      "heightPolicy" : "naturalSize",
      "horzGravity" : "left",
      "label" : "Email",
      "labelColor" : "#000000",
      "labelStyle" : "plain",
      "name" : "inputString30",
      "optional" : false,
      "placeholder" : "",
      "row" : -1,
      "type" : "InputString",
      "uuid" : "73c89052-555c-4ee9-8477-4fc9f7399c30",
      "v" : 16,
      "vertGravity" : "center",
      "w" : 480,
      "widthPolicy" : "explicit"
    }, {
      "backgroundColor" : "#f5f5f5",
      "borderColor" : "Default",
      "borderRadius" : 4,
      "borderThickness" : 1,
      "children" : [ "ca6467dd-8e0b-4480-847d-4475e39c538b", "24553139-dac0-4211-9769-5b9e6d4f9139", "0a9d556a-8caf-4c9b-bf67-4cbd5a28e7a8", "223f3436-b51e-4670-a024-dbf95de23b9f", "73c89052-555c-4ee9-8477-4fc9f7399c30", "17c49f1d-baa9-4331-a8a3-3675769655c6", "9a8170de-29ea-4f90-9f4f-58f387abe0db", "63ebdd1d-8e60-4d7a-8a55-9a00fb94ea67" ],
      "heightPolicy" : "naturalSize",
      "horzGravity" : "center",
      "innerMargin" : 20,
      "name" : "FlowLayout103",
      "type" : "FlowLayout",
      "uuid" : "7b16e4f8-6352-45c9-8280-157d6ba18449",
      "v" : 16,
      "vertGravity" : "center",
      "w" : 1010,
      "widthPolicy" : "explicit",
      "x" : 50,
      "y" : 70
    }, {
      "borderColor" : "Default",
      "borderRadius" : 4,
      "borderThickness" : 0,
      "buttonBackgroundColor" : "platform",
      "buttonLabel" : "Reset",
      "buttonLabelColor" : "platform",
      "buttonLabelSize" : 18,
      "buttonLabelStyle" : "plain",
      "heightPolicy" : "naturalSize",
      "horzGravity" : "left",
      "labelAlign" : "center",
      "labelColor" : "#000000",
      "labelStyle" : "plain",
      "name" : "resettechBtn",
      "submitValue" : 100,
      "type" : "Button",
      "uuid" : "93218a81-b063-4123-ac8b-a3029e6f8723",
      "v" : 16,
      "vertGravity" : "center",
      "widthPolicy" : "sizeToCell"
    }, {
      "binding" : "page.data.Technicians.supportRadius",
      "borderColor" : "Default",
      "borderRadius" : 4,
      "borderThickness" : 0,
      "default" : 50,
      "enumeratedList" : [ {
        "label" : "50 Kilometers Radius",
        "value" : 50
      }, {
        "label" : "100 Kilometers Radius",
        "value" : 100
      }, {
        "label" : "150 Kilometers Radius",
        "value" : 150
      }, {
        "label" : "5000 Kilometers Radius",
        "value" : 5000
      } ],
      "heightPolicy" : "naturalSize",
      "horzGravity" : "center",
      "label" : "Support Radius",
      "labelColor" : "#000000",
      "labelStyle" : "plain",
      "name" : "droplist9306",
      "type" : "Droplist",
      "uuid" : "9a331708-d52b-4c10-8d96-8fca732d04ce",
      "v" : 16,
      "vertGravity" : "center",
      "widthPolicy" : "sizeToCell"
    }, {
      "binding" : "page.data.Technicians.address",
      "borderColor" : "Default",
      "borderRadius" : 4,
      "borderThickness" : 0,
      "defaultValue" : "",
      "heightPolicy" : "naturalSize",
      "horzGravity" : "center",
      "label" : "Address",
      "labelColor" : "#000000",
      "labelStyle" : "plain",
      "name" : "MultilineInput98",
      "optional" : true,
      "placeholder" : "",
      "rows" : 5,
      "type" : "MultilineInput",
      "uuid" : "9a8170de-29ea-4f90-9f4f-58f387abe0db",
      "v" : 16,
      "vertGravity" : "top",
      "w" : 480,
      "widthPolicy" : "explicit",
      "wordwrap" : true
    }, {
      "binding" : "page.data.Technicians.company",
      "borderColor" : "Default",
      "borderRadius" : 4,
      "borderThickness" : 0,
      "column" : -1,
      "defaultValue" : "",
      "heightPolicy" : "naturalSize",
      "horzGravity" : "left",
      "label" : "Company",
      "labelColor" : "#000000",
      "labelStyle" : "plain",
      "name" : "inputString3",
      "optional" : false,
      "placeholder" : "",
      "row" : -1,
      "type" : "InputString",
      "uuid" : "ca6467dd-8e0b-4480-847d-4475e39c538b",
      "v" : 16,
      "vertGravity" : "center",
      "w" : 480,
      "widthPolicy" : "explicit"
    }, {
      "borderColor" : "Default",
      "borderRadius" : 4,
      "borderThickness" : 0,
      "buttonBackgroundColor" : "platform",
      "buttonLabel" : "Submit",
      "buttonLabelColor" : "platform",
      "buttonLabelSize" : 18,
      "buttonLabelStyle" : "plain",
      "heightPolicy" : "naturalSize",
      "horzGravity" : "left",
      "labelAlign" : "center",
      "labelColor" : "#000000",
      "labelStyle" : "plain",
      "name" : "addtechBtn",
      "submitValue" : 100,
      "type" : "Button",
      "uuid" : "dac9873c-c7bf-40fc-af7e-1f74f9f92630",
      "v" : 16,
      "vertGravity" : "center",
      "widthPolicy" : "naturalSize"
    }, {
      "borderColor" : "Default",
      "borderRadius" : 4,
      "borderThickness" : 0,
      "children" : [ "dac9873c-c7bf-40fc-af7e-1f74f9f92630", "93218a81-b063-4123-ac8b-a3029e6f8723" ],
      "heightPolicy" : "naturalSize",
      "horzGravity" : "left",
      "innerMargin" : 20,
      "name" : "HorizontalContainer8162",
      "type" : "HorizontalLayout",
      "uuid" : "dbd598c7-52b4-4487-893c-969c64a8924d",
      "v" : 16,
      "vertGravity" : "bottom",
      "w" : 300,
      "widthPolicy" : "explicit",
      "x" : 50,
      "y" : 1000
    } ]
  },
  "data" : {
    "properties" : {
      "Technicians" : {
        "defaultLabel" : "Technicians",
        "type" : "TypedObject",
        "typedObject" : {
          "properties" : {
            "address" : {
              "defaultLabel" : "address",
              "type" : "String"
            },
            "company" : {
              "defaultLabel" : "company",
              "type" : "String"
            },
            "email" : {
              "defaultLabel" : "email",
              "type" : "String"
            },
            "fname" : {
              "defaultLabel" : "fname",
              "type" : "String"
            },
            "geolocation" : {
              "defaultLabel" : "geolocation",
              "type" : "GeoJSON"
            },
            "lname" : {
              "defaultLabel" : "lname",
              "type" : "String"
            },
            "mobile_phone" : {
              "defaultLabel" : "mobile_phone",
              "type" : "String"
            },
            "mobilegeolocation" : {
              "defaultLabel" : "mobilegeolocation",
              "type" : "GeoJSON"
            },
            "skills" : {
              "defaultLabel" : "skills",
              "isArray" : true,
              "type" : "String"
            },
            "supportRadius" : {
              "defaultLabel" : "supportRadius",
              "defaultValue" : 50,
              "type" : "Integer"
            },
            "username" : {
              "defaultLabel" : "username",
              "type" : "String"
            }
          },
          "type" : "Technicians"
        }
      },
      "dbid" : {
        "defaultLabel" : "dbid",
        "type" : "String"
      }
    }
  },
  "footerChildren" : [ ],
  "hasFooter" : false,
  "layoutType" : "browser",
  "responseTopic" : ""
}