{
  "ars_properties" : {
    "tags" : [ ]
  },
  "ars_public" : false,
  "controllers" : {
    "client" : {
      "customCode" : "RELOCATED to controllers/client/customCode.js"
    },
    "dataStream" : {
      "ce_assets" : { },
      "ce_contacts" : { },
      "ce_skills" : { }
    },
    "page" : {
      "Start" : {
        "onClientStart" : "RELOCATED to controllers/page/Start/onClientStart.js",
        "onStart" : "RELOCATED to controllers/page/Start/onStart.js"
      }
    }
  },
  "isLaunchable" : false,
  "models" : {
    "dataObjects" : {
      "__GLOBAL__" : {
        "properties" : {
          "fullname" : {
            "defaultLabel" : "fullname",
            "type" : "String"
          }
        }
      },
      "__PARAMETERS__" : {
        "properties" : { }
      }
    },
    "dataStreams" : [ {
      "advancedWhereClause" : null,
      "dataObjectName" : null,
      "dataTypeList" : [ {
        "label" : null,
        "type" : "Assets"
      } ],
      "isDeleteOp" : false,
      "isInsertOp" : false,
      "isUpdateOp" : false,
      "maxRecords" : 0,
      "name" : "ce_assets",
      "pauseAtStartup" : false,
      "sortByProperty" : null,
      "sortDescending" : false,
      "type" : 5,
      "updateInterval" : 60,
      "uuid" : "9bb783c3-98de-4538-8067-2121bccda171",
      "v" : 1
    }, {
      "advancedWhereClause" : null,
      "dataObjectName" : null,
      "dataTypeList" : [ {
        "label" : null,
        "type" : "Contacts"
      } ],
      "isDeleteOp" : false,
      "isInsertOp" : false,
      "isUpdateOp" : false,
      "maxRecords" : 0,
      "name" : "ce_contacts",
      "pauseAtStartup" : false,
      "sortByProperty" : null,
      "sortDescending" : false,
      "type" : 5,
      "updateInterval" : 60,
      "uuid" : "e0c51b42-5086-4a0a-8e38-f25846f10482",
      "v" : 1
    }, {
      "advancedWhereClause" : null,
      "dataObjectName" : null,
      "dataTypeList" : [ {
        "label" : null,
        "type" : "Skills"
      } ],
      "isDeleteOp" : false,
      "isInsertOp" : false,
      "isUpdateOp" : false,
      "maxRecords" : 0,
      "name" : "ce_skills",
      "pauseAtStartup" : false,
      "sortByProperty" : null,
      "sortDescending" : false,
      "type" : 5,
      "updateInterval" : 60,
      "uuid" : "ce53d706-ce75-4727-87d1-821a1455616e",
      "v" : 1
    } ]
  },
  "name" : "Accept-Reject-Assignment",
  "options" : {
    "RELOCATE" : [ {
      "path" : "controllers",
      "type" : "js"
    }, {
      "path" : "views",
      "type" : "json"
    } ],
    "badgeCount" : 0,
    "cssAssets" : [ "../../docs/public/css/servicedeskmobile.css" ],
    "description" : "",
    "displayName" : "Accept-Reject-Assignment",
    "docAssets" : [ "public/css/servicedeskmobile.css" ],
    "paletteCollapsed" : false,
    "productV" : "7.4o",
    "showCategoryButtons" : false,
    "showCategoryDataDisplay" : false,
    "showCategoryDataInput" : false,
    "showCategoryLayout" : true,
    "showGridWhileEditing" : true,
    "theme" : {
      "backgroundColor" : "#ffffff",
      "borderColor" : "#000000",
      "cardAccentColor" : "#ffffff",
      "cardColor" : "#3c424d",
      "dataDisplayColor" : "#ffffff",
      "dataDisplayColors" : [ "#3cbce1", "#996db8", "#86d557", "#ff9800", "#425b71", "#cc467c", "#01aa93", "#ffca28", "#f583a9", "#1c84d4", "#ff6767", "#4caf50" ],
      "dataInputColor" : "#ffffff",
      "foregroundColor" : "#000000",
      "label" : "Custom",
      "name" : "custom",
      "titleBarColor" : "#f0f2f8",
      "v" : 3
    },
    "v" : 5
  },
  "targetDevice" : "mobile",
  "userList" : [ ],
  "views" : {
    "Start" : "RELOCATED to views/Start.json"
  }
}